flamespectrum/__init__.py
flamespectrum/blackbody.py
flamespectrum-0.0.3.dist-info/DESCRIPTION.rst
flamespectrum-0.0.3.dist-info/METADATA
flamespectrum-0.0.3.dist-info/RECORD
flamespectrum-0.0.3.dist-info/WHEEL
flamespectrum-0.0.3.dist-info/metadata.json
flamespectrum-0.0.3.dist-info/top_level.txt
flamespectrum-0.0.3.dist-info/zip-safe
