Metadata-Version: 2.0
Name: flamespectrum
Version: 0.0.3
Summary: A Python library for calculate Flame Spectrum.
Home-page: UNKNOWN
Author: lqhtq
Author-email: lqhtq007@gmail.com
License: MIT
Platform: UNKNOWN
Classifier: License :: OSI Approved :: MIT License
Classifier: Operating System :: Microsoft
Classifier: Programming Language :: Python :: 2.6
Classifier: Programming Language :: Python :: 2.7
Classifier: Programming Language :: Python :: 3.3
Classifier: Programming Language :: Python :: 3.4
Classifier: Programming Language :: Python :: 3.5
Classifier: Programming Language :: Python :: 3.6
Requires-Dist: numpy
